bdmc-0.2.6.1.dist-info/METADATA
bdmc-0.2.6.1.dist-info/WHEEL
bdmc-0.2.6.1.dist-info/entry_points.txt
bdmc/__init__.py
bdmc/modules/cmd.py
bdmc/modules/controller.py
bdmc/modules/logger.py
bdmc/modules/port.py
bdmc-0.2.6.1.dist-info/RECORD
